{
    "version": "0.17.1",
    "description": "Looks like JavaScript, feels like Ruby, and it is a script language fitting in C programmers.",
    "homepage": "https://github.com/Kray-G/kinx",
    "license": "MIT",
    "architecture": {
        "64bit": {
            "url": "https://github.com/Kray-G/kinx/releases/download/v0.17.1/package_win64.zip",
            "hash": "efbd729beb9218e699363347d5853c0e681b128838dbb41637aa571abc663545"
        }
    },
    "bin": [
        "kinx.exe",
        "kxkitty.exe",
        "kxrepl.exe",
        "kxtest.exe"
    ],
    "checkver": "github",
    "autoupdate": {
        "architecture": {
            "64bit": {
                "url": "https://github.com/Kray-G/kinx/releases/download/v$version/package_win64.zip"
            }
        }
    }
}
